philosophy/__init__.py
philosophy-0.0.0.dist-info/DESCRIPTION.rst
philosophy-0.0.0.dist-info/METADATA
philosophy-0.0.0.dist-info/RECORD
philosophy-0.0.0.dist-info/WHEEL
philosophy-0.0.0.dist-info/metadata.json
philosophy-0.0.0.dist-info/top_level.txt
