Metadata-Version: 2.0
Name: philosophy
Version: 0.0.0
Summary: --- shameless appropriation of cultural capital
